filesnitch.py
filesnitch-0.2.0.dist-info/LICENSE
filesnitch-0.2.0.dist-info/METADATA
filesnitch-0.2.0.dist-info/WHEEL
filesnitch-0.2.0.dist-info/top_level.txt
filesnitch-0.2.0.dist-info/RECORD
