Metadata-Version: 2.1
Name: filesnitch
Version: 0.2.0
Summary: Snitch up multipart files as one read-only file object
Home-page: https://github.com/righthandabacus/filesnitch
Author: Adrian S.-W. Tam
Author-email: adrian.sw.tam @ gmail.com
License: LGPL
Platform: UNKNOWN
Classifier: Development Status :: 4 - Beta
Classifier: Programming Language :: Python :: 3
Classifier: Intended Audience :: Developers
Classifier: License :: OSI Approved :: GNU Lesser General Public License v3 or later (LGPLv3+)
Classifier: Operating System :: OS Independent
Classifier: Topic :: Software Development
Classifier: Topic :: Software Development :: Libraries :: Python Modules
